{
  "accentColor": "{{appsmith.theme.colors.primaryColor}}",
  "alignWidget": "LEFT",
  "animateLoading": true,
  "borderRadius": "{{appsmith.theme.borderRadius.appBorderRadius}}",
  "bottomRow": 22,
  "defaultCheckedState": false,
  "dynamicBindingPathList": [
    {
      "key": "accentColor"
    },
    {
      "key": "borderRadius"
    }
  ],
  "dynamicHeight": "FIXED",
  "dynamicTriggerPathList": [],
  "isDisabled": false,
  "isLoading": false,
  "isRequired": false,
  "isVisible": true,
  "key": "emicjav97b",
  "label": "",
  "labelPosition": "Left",
  "labelTextSize": "0.875rem",
  "leftColumn": 0,
  "maxDynamicHeight": 9000,
  "minDynamicHeight": 4,
  "minWidth": 450,
  "mobileBottomRow": 8,
  "mobileLeftColumn": 48,
  "mobileRightColumn": 60,
  "mobileTopRow": 4,
  "needsErrorInfo": false,
  "originalBottomRow": 22,
  "originalTopRow": 18,
  "parentColumnSpace": 2.1396484375,
  "parentId": "tikuyzx22p",
  "parentRowSpace": 10,
  "renderMode": "CANVAS",
  "responsiveBehavior": "fill",
  "rightColumn": 37,
  "topRow": 18,
  "type": "CHECKBOX_WIDGET",
  "version": 1,
  "widgetId": "d15cx27n14",
  "widgetName": "Cb_CUSTOM_StartPage"
}